<?xml version="1.0" encoding = "GBK"?>
	<root>
		<head>			
			<tr_code>700002</tr_code>
			<corp_no>00000001</corp_no>
			<req_no>10000000001</req_no>			
			<serial_no>1</serial_no>
			<ans_no>1</ans_no>
			<next_no>1</next_no>
			<tr_acdt>1</tr_acdt>
			<tr_time>1</tr_time>
			<ans_code>[@setVariable,recode,10,0,0@]</ans_code>
			<ans_info>[@setVariable,msg,200,0,0@]</ans_info>
			<particular_code>1</particular_code>
			<atom_tr_count></atom_tr_count>
			<reserved>1</reserved>
			<particular_info>1</particular_info>
		</head>
		<body>			
			<lpaym>[@setVariable,lastpaydate,10,0,0@]</lpaym>
			<bal>[@setVariable,balance,30,0,0@]</bal>
			<accname>[@setVariable,accname,100,0,0@]</accname>
			<accnum>[@setVariable,accnum,50,0,0@]</accnum>
			<basenum>2630.00</basenum>
			<certinum>1</certinum>
			<indipaysum>420.80</indipaysum>
			<opnaccdate>2007-01-01</opnaccdate>
			<unitaccname>[@setVariable,unitaccname,100,0,0@]</unitaccname>
			<unitaccnum>[@setVariable,unitaccnum,50,0,0@]</unitaccnum>
			<state>0</state>
			<frzflag>0</frzflag>
			<frzamt>0.00</frzamt>
			<indipayamt>157.80</indipayamt>
			<unitpayamt>263.00</unitpayamt>
			<unitprop>0.100</unitprop>
			<indiprop>0.060</indiprop>
		</body>
	</root>			
